{
  "main": {
    "id": "412aefb367fe195b",
    "type": "split",
    "children": [
      {
        "id": "83e2fe604ff2cec5",
        "type": "tabs",
        "children": [
          {
            "id": "eaa6966bab08c527",
            "type": "leaf",
            "state": {
              "type": "empty",
              "state": {}
            }
          }
        ]
      }
    ],
    "direction": "vertical"
  },
  "left": {
    "id": "36f9154d784770a6",
    "type": "split",
    "children": [
      {
        "id": "d601c24d1851d79b",
        "type": "tabs",
        "children": [
          {
            "id": "ea1ac836485814cc",
            "type": "leaf",
            "state": {
              "type": "file-explorer",
              "state": {
                "sortOrder": "alphabetical"
              }
            }
          },
          {
            "id": "db095b022f573fd1",
            "type": "leaf",
            "state": {
              "type": "search",
              "state": {
                "query": "",
                "matchingCase": false,
                "explainSearch": false,
                "collapseAll": false,
                "extraContext": false,
                "sortOrder": "alphabetical"
              }
            }
          },
          {
            "id": "0a0ccd27a8b422b4",
            "type": "leaf",
            "state": {
              "type": "bookmarks",
              "state": {}
            }
          }
        ]
      }
    ],
    "direction": "horizontal",
    "width": 300
  },
  "right": {
    "id": "b978287e95904d70",
    "type": "split",
    "children": [
      {
        "id": "db0fc6599aadd894",
        "type": "tabs",
        "children": [
          {
            "id": "55ab0448f6ad8614",
            "type": "leaf",
            "state": {
              "type": "backlink",
              "state": {
                "collapseAll": false,
                "extraContext": false,
                "sortOrder": "alphabetical",
                "showSearch": false,
                "searchQuery": "",
                "backlinkCollapsed": false,
                "unlinkedCollapsed": true
              }
            }
          },
          {
            "id": "de58873806bd0593",
            "type": "leaf",
            "state": {
              "type": "outgoing-link",
              "state": {
                "linksCollapsed": false,
                "unlinkedCollapsed": true
              }
            }
          },
          {
            "id": "e47bb0fae13f80e4",
            "type": "leaf",
            "state": {
              "type": "tag",
              "state": {
                "sortOrder": "frequency",
                "useHierarchy": true
              }
            }
          },
          {
            "id": "215851af7027d2e2",
            "type": "leaf",
            "state": {
              "type": "outline",
              "state": {}
            }
          }
        ]
      }
    ],
    "direction": "horizontal",
    "width": 300,
    "collapsed": true
  },
  "left-ribbon": {
    "hiddenItems": {
      "switcher:Open quick switcher": false,
      "graph:Open graph view": false,
      "canvas:Create new canvas": false,
      "daily-notes:Open today's daily note": false,
      "templates:Insert template": false,
      "command-palette:Open command palette": false
    }
  },
  "active": "eaa6966bab08c527",
  "lastOpenFiles": [
    "content/Novels/The Moon is a Harsh Mistress.md",
    "content/Novels/Untitled.md"
  ]
}